jspline/__init__.py
jspline/jspline.py
jspline-1.0.3.dist-info/LICENSE.txt
jspline-1.0.3.dist-info/METADATA
jspline-1.0.3.dist-info/WHEEL
jspline-1.0.3.dist-info/top_level.txt
jspline-1.0.3.dist-info/RECORD
