Metadata-Version: 2.1
Name: jspline
Version: 1.0.3
Summary: Multi-dimensional parameterized spline curves (snappiness parameter gives uniform cubic B-splines, four-point subdivision splines, uniform quintic B-splines, and everything in-between)
Home-page: https://github.com/gitcnd/jspline
Author: Chris Drake
Author-email: cnd@geek.net.au
License: MIT
Download-URL: https://pypi.org/project/jspline/
Keywords: J-Spline,spline,B-spline,curves,interpolation
Platform: UNKNOWN
